{
  "Name": "Marrickville Council Archival Reference Centre",
  "URL": "/archives/106",
  "About": [
    {
      "Officer in charge": "Council Archivist"
    },
    {
      "Hours & facilities": "Open Tues 10am-1pm and 2-4pm and by appointment other days. General reference assistance available. Copying services available for books, journals, microfiche, photographs, newspapers, maps and plans. Introductory brochure available."
    },
    {
      "Access": "All public access is by daily ticket approved on the spot. Proof of identity required. Access to records not normally available for research can be gained by authorisation from General Manager/Town Clerk and Council."
    },
    {
      "Acquisition focus": "The Archival Reference Centre is an in-house archives and does not receive records from any other source than Council and its predecessors."
    },
    {
      "Quantity": "300m (99% in-house)."
    },
    {
      "Major holdings": "Marrickville Municipal Council: Rate, assessment/valuation books 1886-1950 (100m); Rate books 1880s-1930s (50m); Minute books 1913-1940s (6m); Field books 1897 (0.33m); Building applications and development applications 1950's-1980s (70m). Petersham Municipal Council: Rate, assessment/valuation books 1872-1948 (40m); Rate and minute books 1872-1948 (30m); Building/Subdivision books 1911-1940s (.06m). St Peters Municipal Council: Rate assessment/valuation books 1871-1948 (60m); Rate and minute books 1871-1948 (40m); Building subdivision books 1911-1940s (0.03m)."
    },
    {
      "References": "Cashman, Richard & Meader, ChrysMarrickville, Rural Outpost to Inner City. Hale and Iremonger, 1990: 215-216 Marrickville Heritage Society,Heritage Vol. 5 (1989): 46-48"
    }
  ],
  "Contact": [
    {
      "Street address": "Petersham Town Hall, Crystal Street, Petersham 2049"
    },
    {
      "Postal address": "PO Box 14, Petersham 2049"
    },
    {
      "Phone": "(02) 9335-2185"
    },
    {
      "Fax": "(02) 9335-2029"
    },
    {
      "Website": "http://www.marrickville.nsw.gov.au/"
    }
  ]
}
