{
  "Name": "Australian Catholic University, Castle Hill Campus",
  "URL": "/archives/32",
  "About": [
    {
      "Officer in charge": "Archivist"
    },
    {
      "Hours & facilities": "Open University working days."
    },
    {
      "Acquisition focus": "Materials relating to the academic and social life of the former Colleges, now the University."
    }
  ],
  "Contact": [
    {
      "Street address": "Old Northern Road, Castle Hill 2154"
    },
    {
      "Postal address": "As above"
    },
    {
      "Phone": "(02) 9899-8000"
    },
    {
      "Fax": "(02) 9899-8005"
    }
  ]
}
