{
  "Name": "Sisters of Charity of Australia",
  "URL": "/archives/158",
  "About": [
    {
      "Officer in charge": "Archivist-in-charge"
    },
    {
      "Hours & facilities": "Open Mon., Tues., Wed., Thurs. and Fri. 10 a.m. to 3.30 p.m; closed Christmas-New Year period.  General reference assistance available in person in Research Room, by mail or telephone;  guided tours to Museum and Archives displays by prior arrangement.  Copying services available."
    },
    {
      "Access": "Advance notice of visit required . Access restrictions apply to certain records."
    },
    {
      "Acquisition focus": "The Archive holds the records of this Catholic religious congregation (its governing and administrative bodies, individual members, convents) and of the facilities it continues or used to conduct / own in the field of health and aged care, education, social welfare and other charitable ventures in New South Wales, Victoria, Tasmania, Queensland and the Australian Capital Territory, and in overseas missions in the Pacific, from 1838 to date. In addition to standard paper-based archival holdings, the Archives include a rare book collection, artefacts, photographs, textiles and a reference library."
    },
    {
      "Quantity": "280 linear metres (100% in-house)."
    }
  ],
  "Contact": [
    {
      "Street address": "Rockwall Crescent, Potts Point 2011"
    },
    {
      "Postal address": "PO Box 21, Potts Point 2100"
    },
    {
      "Phone": "(02) 9356-3294"
    },
    {
      "Fax": "(02) 9358-6830"
    },
    {
      "Email": "arcinfo@pacific.net.au"
    }
  ]
}
