{
  "Name": "Alice Springs Collection",
  "URL": "/archives/207",
  "About": [
    {
      "Officer in charge": "Jane Bowland and Mandy Treloar"
    },
    {
      "Hours & facilities": "Open Mon, Tues and Thurs 10-6, Wed and Fri 10-5, Sat 9-1, Sun 1-5.; closed public holidays. General reference assistance available. Copying services available for books, journals, original records to A3 and newspapers."
    },
    {
      "Acquisition focus": "Focus is on materials published or produced in the Alice Springs area. This area ranges from Pt Augusta to Tennant Creek and to the N.T. borders east and west of Alice Springs."
    },
    {
      "Major holdings": "Robert Laver: Photographs 1921-1925 (1m). Old Timer's Museum: Photographs 1900 - 1970s (1m)."
    }
  ],
  "Contact": [
    {
      "Street address": "Corner Leichhardt and Gregory Terrace, Alice Springs 0870"
    },
    {
      "Postal address": "PO Box 1071, Alice Springs 0871"
    },
    {
      "Phone": "(08) 8950-0555"
    },
    {
      "Fax": "(08) 8952-2402"
    }
  ]
}
