{
  "Name": "Canberra Girls' Grammar School",
  "URL": "/archives/493",
  "About": [
    {
      "Officer in charge": "Archivist"
    },
    {
      "Hours & facilities": "Contact Archivist Monday to Thursday."
    },
    {
      "Access": "In writing to Principal or Archivist."
    },
    {
      "Acquisition focus": "Records created by school and other organisations directly related to it."
    }
  ],
  "Contact": [
    {
      "Street address": "Melbourne Avenue, Deakin, ACT 2600"
    },
    {
      "Postal address": "As above"
    },
    {
      "Phone": "(02) 6202-6457"
    },
    {
      "Fax": "(02) 6273-1505"
    },
    {
      "Email": "archives@cggs.act.edu.au"
    }
  ]
}
