{
  "Name": "Australian Jockey Club Racing Museum",
  "URL": "/archives/36",
  "About": [
    {
      "Hours & facilities": "Open Fri 9am-2pm by appointment. Reference assistance available in person. Copying services available for books, journals, photographs and newspapers."
    },
    {
      "Access": "2-3 days' advance notice of visit required."
    },
    {
      "Acquisition focus": "Archives have been acquired from various sources within the Australian Jockey Club and outside donations. Most reference material is obtained from the Library. (80% in-house)."
    }
  ],
  "Contact": [
    {
      "Street address": "Randwick Racecourse, Alison Road, Randwick 2031"
    },
    {
      "Postal address": "PO Box 3, Randwick 2031"
    },
    {
      "Phone": "(02) 9663-8400"
    },
    {
      "Fax": "(02) 9662-6292"
    },
    {
      "Website": "http://www.ajc.org.au/"
    }
  ]
}
